{
  "$schema": "https://json.schemastore.org/tsconfig",
  "display": "Default",
  "compilerOptions": {
    "target": "ES6",
    "module": "ESNext",
    "composite": false,
    "declaration": true,
    "declarationMap": true,
    "esModuleInterop": true,
    "inlineSources": false,
    "isolatedModules": true,
    "preserveWatchOutput": true,
    "strict": true,
    "moduleResolution": "node",
    "importHelpers": true,
    "allowSyntheticDefaultImports": true,
    "experimentalDecorators": true,
    "emitDecoratorMetadata": true,
    "noLib": false,
    "preserveConstEnums": true,
    "suppressImplicitAnyIndexErrors": true,
    "sourceMap": true,
    "baseUrl": "src",
    "strictNullChecks": true,
    "noImplicitAny": true,
    "noImplicitThis": true,
    "noImplicitUseStrict": false,
    "noUnusedLocals": true,
    "noUnusedParameters": true,
    "removeComments": false,
    "lib": ["es2017", "dom", "dom.iterable", "scripthost"],
    "skipLibCheck": true,
    "downlevelIteration": true,
    "forceConsistentCasingInFileNames": true
  },
  "exclude": ["node_modules", "**/__tests__/*"]
}
